{
  "tables": [{
      "name": "Properties",
      "displayName": "Properties",
      "isSystem": false,
      "fields": [{
          "name": "pictures",
          "displayName": "Pictures",
          "description": null,
          "fieldType": "FILE",
          "fieldTypeAttributes": {
            "format": "IMAGE",
            "maxSize": null,
            "typeRestrictions": null
          },
          "isList": true,
          "isRequired": false,
          "isUnique": null,
          "defaultValue": null,
          "relation": null
        },
        {
          "name": "bedrooms",
          "displayName": "Bedrooms",
          "description": null,
          "fieldType": "NUMBER",
          "fieldTypeAttributes": {
            "format": "NUMBER",
            "precision": 0,
            "currency": null,
            "minValue": 0,
            "maxValue": null
          },
          "isList": false,
          "isRequired": false,
          "isUnique": false,
          "defaultValue": null,
          "relation": null
        },
        {
          "name": "title",
          "displayName": "title",
          "description": null,
          "fieldType": "TEXT",
          "fieldTypeAttributes": {
            "format": "UNFORMATTED",
            "fieldSize": 500
          },
          "isList": false,
          "isRequired": false,
          "isUnique": false,
          "defaultValue": null,
          "relation": null
        },
        {
          "name": "description",
          "displayName": "Description",
          "description": null,
          "fieldType": "TEXT",
          "fieldTypeAttributes": {
            "format": "UNFORMATTED",
            "fieldSize": 500
          },
          "isList": false,
          "isRequired": false,
          "isUnique": false,
          "defaultValue": null,
          "relation": null
        },
        {
          "name": "sqFootage",
          "displayName": "Sq Footage",
          "description": null,
          "fieldType": "NUMBER",
          "fieldTypeAttributes": {
            "format": "NUMBER",
            "precision": 0,
            "currency": null,
            "minValue": 0,
            "maxValue": null
          },
          "isList": false,
          "isRequired": false,
          "isUnique": false,
          "defaultValue": null,
          "relation": null
        },
        {
          "name": "bathrooms",
          "displayName": "Bathrooms",
          "description": null,
          "fieldType": "NUMBER",
          "fieldTypeAttributes": {
            "format": "NUMBER",
            "precision": 0,
            "currency": null,
            "minValue": 0,
            "maxValue": null
          },
          "isList": false,
          "isRequired": false,
          "isUnique": false,
          "defaultValue": null,
          "relation": null
        },
        {
          "name": "garage",
          "displayName": "Garage",
          "description": null,
          "fieldType": "SWITCH",
          "fieldTypeAttributes": {
            "format": "YES_NO",
            "listOptions": null
          },
          "isList": false,
          "isRequired": false,
          "isUnique": null,
          "defaultValue": false,
          "relation": null
        },
        {
          "name": "pool",
          "displayName": "Pool",
          "description": null,
          "fieldType": "SWITCH",
          "fieldTypeAttributes": {
            "format": "YES_NO",
            "listOptions": null
          },
          "isList": false,
          "isRequired": false,
          "isUnique": null,
          "defaultValue": false,
          "relation": null
        },
        {
          "name": "listings",
          "displayName": "Listings",
          "description": null,
          "fieldType": "RELATION",
          "fieldTypeAttributes": null,
          "isList": true,
          "isRequired": false,
          "isUnique": null,
          "defaultValue": null,
          "relation": {
            "refFieldIsList": false,
            "refFieldIsRequired": false,
            "refFieldName": "property",
            "refFieldDisplayName": "Property",
            "refTable": {
              "name": "Listings"
            }
          }
        }
      ]
    },
    {
      "name": "Brokers",
      "displayName": "Brokers",
      "isSystem": false,
      "fields": [{
          "name": "user",
          "displayName": "User",
          "description": null,
          "fieldType": "RELATION",
          "fieldTypeAttributes": null,
          "isList": false,
          "isRequired": false,
          "isUnique": null,
          "defaultValue": null,
          "relation": {
            "refFieldIsList": true,
            "refFieldIsRequired": false,
            "refFieldName": "broker",
            "refFieldDisplayName": "Broker",
            "refTable": {
              "name": "Users"
            }
          }
        },
        {
          "name": "listings",
          "displayName": "Listings",
          "description": null,
          "fieldType": "RELATION",
          "fieldTypeAttributes": null,
          "isList": true,
          "isRequired": false,
          "isUnique": null,
          "defaultValue": null,
          "relation": {
            "refFieldIsList": false,
            "refFieldIsRequired": false,
            "refFieldName": "broker",
            "refFieldDisplayName": "Broker",
            "refTable": {
              "name": "Listings"
            }
          }
        }
      ]
    },
    {
      "name": "Customers",
      "displayName": "Customers",
      "isSystem": false,
      "fields": [{
          "name": "user",
          "displayName": "User",
          "description": null,
          "fieldType": "RELATION",
          "fieldTypeAttributes": null,
          "isList": false,
          "isRequired": false,
          "isUnique": null,
          "defaultValue": null,
          "relation": {
            "refFieldIsList": true,
            "refFieldIsRequired": false,
            "refFieldName": "customer",
            "refFieldDisplayName": "Customer",
            "refTable": {
              "name": "Users"
            }
          }
        },
        {
          "name": "purchases",
          "displayName": "Purchases",
          "description": null,
          "fieldType": "RELATION",
          "fieldTypeAttributes": null,
          "isList": true,
          "isRequired": false,
          "isUnique": null,
          "defaultValue": null,
          "relation": {
            "refFieldIsList": false,
            "refFieldIsRequired": false,
            "refFieldName": "buyer",
            "refFieldDisplayName": "Buyer",
            "refTable": {
              "name": "Listings"
            }
          }
        },
        {
          "name": "sales",
          "displayName": "Sales",
          "description": null,
          "fieldType": "RELATION",
          "fieldTypeAttributes": null,
          "isList": true,
          "isRequired": false,
          "isUnique": null,
          "defaultValue": null,
          "relation": {
            "refFieldIsList": false,
            "refFieldIsRequired": false,
            "refFieldName": "seller",
            "refFieldDisplayName": "Seller",
            "refTable": {
              "name": "Listings"
            }
          }
        }
      ]
    },
    {
      "name": "Listings",
      "displayName": "Listings",
      "isSystem": false,
      "fields": [{
          "name": "documents",
          "displayName": "Documents",
          "description": null,
          "fieldType": "FILE",
          "fieldTypeAttributes": {
            "format": "FILE",
            "maxSize": null,
            "typeRestrictions": null
          },
          "isList": true,
          "isRequired": false,
          "isUnique": null,
          "defaultValue": null,
          "relation": null
        },
        {
          "name": "buyer",
          "displayName": "Buyer",
          "description": null,
          "fieldType": "RELATION",
          "fieldTypeAttributes": null,
          "isList": false,
          "isRequired": false,
          "isUnique": null,
          "defaultValue": null,
          "relation": {
            "refFieldIsList": true,
            "refFieldIsRequired": false,
            "refFieldName": "purchases",
            "refFieldDisplayName": "Purchases",
            "refTable": {
              "name": "Customers"
            }
          }
        },
        {
          "name": "seller",
          "displayName": "Seller",
          "description": null,
          "fieldType": "RELATION",
          "fieldTypeAttributes": null,
          "isList": false,
          "isRequired": false,
          "isUnique": null,
          "defaultValue": null,
          "relation": {
            "refFieldIsList": true,
            "refFieldIsRequired": false,
            "refFieldName": "sales",
            "refFieldDisplayName": "Sales",
            "refTable": {
              "name": "Customers"
            }
          }
        },
        {
          "name": "status",
          "displayName": "Status",
          "description": null,
          "fieldType": "SWITCH",
          "fieldTypeAttributes": {
            "format": "CUSTOM",
            "listOptions": [
              "Lead",
              "Closing",
              "Active",
              "Closed",
              "Cancelled"
            ]
          },
          "isList": false,
          "isRequired": false,
          "isUnique": null,
          "defaultValue": null,
          "relation": null
        },
        {
          "name": "closingDate",
          "displayName": "Closing Date",
          "description": null,
          "fieldType": "DATE",
          "fieldTypeAttributes": {
            "format": "DATE"
          },
          "isList": false,
          "isRequired": false,
          "isUnique": false,
          "defaultValue": null,
          "relation": null
        },
        {
          "name": "price",
          "displayName": "Price",
          "description": null,
          "fieldType": "NUMBER",
          "fieldTypeAttributes": {
            "format": "NUMBER",
            "precision": 2,
            "currency": null,
            "minValue": 0,
            "maxValue": null
          },
          "isList": false,
          "isRequired": false,
          "isUnique": false,
          "defaultValue": null,
          "relation": null
        },
        {
          "name": "broker",
          "displayName": "Broker",
          "description": null,
          "fieldType": "RELATION",
          "fieldTypeAttributes": null,
          "isList": false,
          "isRequired": false,
          "isUnique": null,
          "defaultValue": null,
          "relation": {
            "refFieldIsList": true,
            "refFieldIsRequired": false,
            "refFieldName": "listings",
            "refFieldDisplayName": "Listings",
            "refTable": {
              "name": "Brokers"
            }
          }
        },
        {
          "name": "property",
          "displayName": "Property",
          "description": null,
          "fieldType": "RELATION",
          "fieldTypeAttributes": null,
          "isList": false,
          "isRequired": false,
          "isUnique": null,
          "defaultValue": null,
          "relation": {
            "refFieldIsList": true,
            "refFieldIsRequired": false,
            "refFieldName": "listings",
            "refFieldDisplayName": "Listings",
            "refTable": {
              "name": "Properties"
            }
          }
        }
      ]
    }
  ],
  "data": {
    "Brokers": [{
        "$id": "broker-1",
        "user": {
          "$id": "$currentUserId"
        }
      },
      {
        "$id": "broker-2",
        "user": {
          "$id": "$currentUserId"
        }
      },
      {
        "$id": "broker-3",
        "user": {
          "$id": "$currentUserId"
        }
      },
      {
        "$id": "broker-4",
        "user": {
          "$id": "$currentUserId"
        }
      },
      {
        "$id": "broker-5",
        "user": {
          "$id": "$currentUserId"
        }
      },
      {
        "$id": "broker-6",
        "user": {
          "$id": "$currentUserId"
        }
      },
      {
        "$id": "broker-7",
        "user": {
          "$id": "$currentUserId"
        }
      },
      {
        "$id": "broker-8",
        "user": {
          "$id": "$currentUserId"
        }
      },
      {
        "$id": "broker-9",
        "user": {
          "$id": "$currentUserId"
        }
      },
      {
        "$id": "broker-10",
        "user": {
          "$id": "$currentUserId"
        }
      }
    ],
    "Customers": [{
        "$id": "customer-1",
        "user": {
          "$id": "$currentUserId"
        }
      },
      {
        "$id": "customer-2",
        "user": {
          "$id": "$currentUserId"
        }
      },
      {
        "$id": "customer-3",
        "user": {
          "$id": "$currentUserId"
        }
      },
      {
        "$id": "customer-4",
        "user": {
          "$id": "$currentUserId"
        }
      },
      {
        "$id": "customer-5",
        "user": {
          "$id": "$currentUserId"
        }
      },
      {
        "$id": "customer-6",
        "user": {
          "$id": "$currentUserId"
        }
      },
      {
        "$id": "customer-7",
        "user": {
          "$id": "$currentUserId"
        }
      },
      {
        "$id": "customer-8",
        "user": {
          "$id": "$currentUserId"
        }
      },
      {
        "$id": "customer-9",
        "user": {
          "$id": "$currentUserId"
        }
      },
      {
        "$id": "customer-10",
        "user": {
          "$id": "$currentUserId"
        }
      }
    ],
    "Properties": [{
      "$id": "property-1",
      "pictures": [{
        "fileId": "4t6usZX5Tc6QyA2GisXA",
        "public": true,
        "filename": "house.jpeg"
      }],
      "bedrooms": 1,
      "title": "Decima",
      "description": "Description",
      "sqFootage": 1000,
      "bathrooms": 2,
      "garage": true,
      "pool": true,
      "listings": [{
        "$id": "listing-1"
      }]
    }, {
      "$id": "property-2",
      "pictures": [{
        "fileId": "B52KS1elSayC3Pqnp3fF",
        "public": true,
        "filename": "house.jpeg"
      }],
      "bedrooms": 1,
      "title": "Counterdefender",
      "description": "Description",
      "sqFootage": 1000,
      "bathrooms": 2,
      "garage": true,
      "pool": true,
      "listings": [{
        "$id": "listing-2"
      }]
    }, {
      "$id": "property-3",
      "pictures": [{
        "fileId": "0yiwgS31RzCMWgI0s0eM",
        "public": true,
        "filename": "house.jpeg"
      }],
      "bedrooms": 1,
      "title": "Beladle",
      "description": "Description",
      "sqFootage": 1000,
      "bathrooms": 2,
      "garage": true,
      "pool": true,
      "listings": [{
        "$id": "listing-3"
      }]
    }, {
      "$id": "property-4",
      "pictures": [{
        "fileId": "trI35UwRw6eQ03FztmBb",
        "public": true,
        "filename": "house.jpeg"
      }],
      "bedrooms": 1,
      "title": "Dragger",
      "description": "Description",
      "sqFootage": 1000,
      "bathrooms": 2,
      "garage": true,
      "pool": true,
      "listings": [{
        "$id": "listing-4"
      }]
    }, {
      "$id": "property-5",
      "pictures": [{
        "fileId": "LgJDMmuMRwqHVtPOULFt",
        "public": true,
        "filename": "house.jpeg"
      }],
      "bedrooms": 1,
      "title": "Hervati",
      "description": "Description",
      "sqFootage": 1000,
      "bathrooms": 2,
      "garage": true,
      "pool": true,
      "listings": [{
        "$id": "listing-5"
      }]
    }, {
      "$id": "property-6",
      "pictures": [{
        "fileId": "PAB7ltMBRFCCebW5j2Wp",
        "public": true,
        "filename": "house.jpeg"
      }],
      "bedrooms": 1,
      "title": "Bagre",
      "description": "Description",
      "sqFootage": 1000,
      "bathrooms": 2,
      "garage": true,
      "pool": true,
      "listings": [{
        "$id": "listing-6"
      }]
    }, {
      "$id": "property-7",
      "pictures": [{
        "fileId": "c7SDtuK0TdOJEHnlOZD5",
        "public": true,
        "filename": "house.jpeg"
      }],
      "bedrooms": 1,
      "title": "Malpractice",
      "description": "Description",
      "sqFootage": 1000,
      "bathrooms": 2,
      "garage": true,
      "pool": true,
      "listings": [{
        "$id": "listing-7"
      }]
    }, {
      "$id": "property-8",
      "pictures": [{
        "fileId": "pgS0Oih6RbaOUa1DIbzt",
        "public": true,
        "filename": "house.jpeg"
      }],
      "bedrooms": 1,
      "title": "Jackbird",
      "description": "Description",
      "sqFootage": 1000,
      "bathrooms": 2,
      "garage": true,
      "pool": true,
      "listings": [{
        "$id": "listing-8"
      }]
    }, {
      "$id": "property-9",
      "pictures": [{
        "fileId": "OMOpW0apR5KJEw8VOruw",
        "public": true,
        "filename": "house.jpeg"
      }],
      "bedrooms": 1,
      "title": "Spheges",
      "description": "Description",
      "sqFootage": 1000,
      "bathrooms": 2,
      "garage": true,
      "pool": true,
      "listings": [{
        "$id": "listing-9"
      }]
    }, {
      "$id": "property-10",
      "pictures": [{
        "fileId": "RuekIdG7QFC7mrYhfcaG",
        "public": true,
        "filename": "house.jpeg"
      }],
      "bedrooms": 1,
      "title": "Mutable",
      "description": "Description",
      "sqFootage": 1000,
      "bathrooms": 2,
      "garage": true,
      "pool": true,
      "listings": [{
        "$id": "listing-10"
      }]
    }],
    "Listings": [{
      "$id": "listing-1",
      "property": {
        "$id": "property-1"
      },
      "broker": {
        "$id": "broker-9"
      },
      "buyer": {
        "$id": "customer-9"
      },
      "seller": {
        "$id": "customer-1"
      },
      "documents": [],
      "status": "Lead",
      "closingDate": null,
      "price": 12345
    }, {
      "$id": "listing-2",
      "property": {
        "$id": "property-2"
      },
      "broker": {
        "$id": "broker-5"
      },
      "buyer": {
        "$id": "customer-10"
      },
      "seller": {
        "$id": "customer-1"
      },
      "documents": [],
      "status": "Lead",
      "closingDate": null,
      "price": 12345
    }, {
      "$id": "listing-3",
      "property": {
        "$id": "property-3"
      },
      "broker": {
        "$id": "broker-5"
      },
      "buyer": {
        "$id": "customer-4"
      },
      "seller": {
        "$id": "customer-8"
      },
      "documents": [],
      "status": "Lead",
      "closingDate": null,
      "price": 12345
    }, {
      "$id": "listing-4",
      "property": {
        "$id": "property-4"
      },
      "broker": {
        "$id": "broker-10"
      },
      "buyer": {
        "$id": "customer-10"
      },
      "seller": {
        "$id": "customer-7"
      },
      "documents": [],
      "status": "Lead",
      "closingDate": null,
      "price": 12345
    }, {
      "$id": "listing-5",
      "property": {
        "$id": "property-5"
      },
      "broker": {
        "$id": "broker-7"
      },
      "buyer": {
        "$id": "customer-3"
      },
      "seller": {
        "$id": "customer-2"
      },
      "documents": [],
      "status": "Lead",
      "closingDate": null,
      "price": 12345
    }, {
      "$id": "listing-6",
      "property": {
        "$id": "property-5"
      },
      "broker": {
        "$id": "broker-7"
      },
      "buyer": {
        "$id": "customer-3"
      },
      "seller": {
        "$id": "customer-2"
      },
      "documents": [],
      "status": "Lead",
      "closingDate": null,
      "price": 12345
    }, {
      "$id": "listing-7",
      "property": {
        "$id": "property-5"
      },
      "broker": {
        "$id": "broker-7"
      },
      "buyer": {
        "$id": "customer-3"
      },
      "seller": {
        "$id": "customer-2"
      },
      "documents": [],
      "status": "Lead",
      "closingDate": null,
      "price": 12345
    }, {
      "$id": "listing-8",
      "property": {
        "$id": "property-5"
      },
      "broker": {
        "$id": "broker-7"
      },
      "buyer": {
        "$id": "customer-3"
      },
      "seller": {
        "$id": "customer-2"
      },
      "documents": [],
      "status": "Lead",
      "closingDate": null,
      "price": 12345
    }, {
      "$id": "listing-9",
      "property": {
        "$id": "property-5"
      },
      "broker": {
        "$id": "broker-7"
      },
      "buyer": {
        "$id": "customer-3"
      },
      "seller": {
        "$id": "customer-2"
      },
      "documents": [],
      "status": "Lead",
      "closingDate": null,
      "price": 12345
    }, {
      "$id": "listing-10",
      "property": {
        "$id": "property-5"
      },
      "broker": {
        "$id": "broker-7"
      },
      "buyer": {
        "$id": "customer-3"
      },
      "seller": {
        "$id": "customer-2"
      },
      "documents": [],
      "status": "Lead",
      "closingDate": null,
      "price": 12345
    }]
  },
  "version": "0.0.44"
}
